{
    "data": [
        {
            "origin": {
                "name": "GHS"
            },
            "result": {
                "name": "GHS"
            }
        },
        {
            "origin": {
                "name": "Chemical"
            },
            "result": {
                "name": "Chemical"
            }
        },
        {
            "origin": {
                "name": "Consult"
            },
            "result": {
                "name": "Consult"
            }
        }
    ]
}